MANIFEST.in
README.md
setup.py
oxen/__init__.py
oxen/color.py
oxen/event.py
oxen/path.py
oxen/process.py
oxen/rsync.py
oxen/session.py
oxen/stream.py
oxen/task.py
oxen/watch.py
oxen/webserver.py
oxen.egg-info/PKG-INFO
oxen.egg-info/SOURCES.txt
oxen.egg-info/dependency_links.txt
oxen.egg-info/requires.txt
oxen.egg-info/top_level.txt
oxen.egg-info/zip-safe
oxen/client/static/css/app.css
oxen/client/static/js/oxen.js
oxen/client/static/js/oxen.js.map
oxen/client/static/templates/app.html